{"result_index": 0, "results": [{"final": true, "alternatives": [{"transcript": "jet ", "confidence": 0.08, "timestamps": [["jet", 0.0, 0.53]]}]}, {"final": true, "alternatives": [{"transcript": "I want to tell you all of it yeah okay tell me the story ", "confidence": 0.4, "timestamps": [["I", 1.55, 1.58], ["want", 2.16, 2.5], ["to", 2.5, 2.62], ["tell", 2.62, 2.79], ["you", 2.79, 2.98], ["all", 2.98, 3.11], ["of", 3.11, 3.24], ["it", 3.24, 3.4], ["yeah", 3.46, 3.7], ["okay", 4.15, 4.64], ["tell", 4.75, 4.9], ["me", 4.9, 5.03], ["the", 5.03, 5.15], ["story", 5.15, 5.61]]}]}, {"final": true, "alternatives": [{"transcript": "full story %HESITATION he was young ", "confidence": 0.64, "timestamps": [["full", 6.89, 7.19], ["story", 7.19, 7.51], ["%HESITATION", 7.61, 8.06], ["he", 8.49, 8.76], ["was", 8.76, 8.99], ["young", 8.99, 9.62]]}]}, {"final": true, "alternatives": [{"transcript": "Denham recall let he was ten and and it looks like peak a new two kisses flew home yay you got it he he could have possibly caused my dad for a ", "confidence": 0.52, "timestamps": [["Denham", 10.43, 11.13], ["recall", 11.13, 11.62], ["let", 11.62, 11.98], ["he", 12.35, 12.51], ["was", 12.51, 12.8], ["ten", 12.8, 13.19], ["and", 13.32, 13.65], ["and", 13.68, 13.9], ["it", 13.9, 14.0], ["looks", 14.0, 14.37], ["like", 14.37, 14.63], ["peak", 14.66, 15.16], ["a", 15.79, 15.91], ["new", 15.91, 16.18], ["two", 16.18, 16.29], ["kisses", 16.29, 16.93], ["flew", 16.93, 17.48], ["home", 17.98, 18.35], ["yay", 18.35, 18.73], ["you", 18.73, 19.09], ["got", 19.61, 19.83], ["it", 19.83, 20.1], ["he", 20.7, 21.01], ["he", 21.04, 21.18], ["could", 21.18, 21.41], ["have", 21.41, 21.52], ["possibly", 21.52, 22.0], ["caused", 22.0, 22.3], ["my", 22.3, 22.4], ["dad", 22.4, 22.91], ["for", 23.59, 23.72], ["a", 23.72, 24.21]]}]}, {"final": true, "alternatives": [{"transcript": "then collect data file ", "confidence": 0.21, "timestamps": [["then", 25.37, 26.18], ["collect", 26.5, 27.06], ["data", 27.44, 27.91], ["file", 27.91, 28.53]]}]}, {"final": true, "alternatives": [{"transcript": "he did a lot of the coaster ", "confidence": 0.3, "timestamps": [["he", 29.64, 29.9], ["did", 29.9, 30.38], ["a", 30.63, 30.74], ["lot", 30.74, 30.87], ["of", 30.87, 30.95], ["the", 30.95, 31.08], ["coaster", 31.08, 31.8]]}]}, {"final": true, "alternatives": [{"transcript": "hello blessed deal much you must select your bottom right jet jet uses the same name ", "confidence": 0.55, "timestamps": [["hello", 32.93, 33.28], ["blessed", 33.28, 33.91], ["deal", 33.91, 34.09], ["much", 34.09, 34.74], ["you", 34.78, 34.91], ["must", 34.91, 35.22], ["select", 35.22, 35.62], ["your", 35.62, 35.79], ["bottom", 35.79, 36.27], ["right", 36.78, 37.43], ["jet", 38.04, 38.39], ["jet", 38.39, 38.71], ["uses", 38.71, 39.22], ["the", 39.22, 39.66], ["same", 40.43, 40.95], ["name", 40.95, 41.2]]}]}, {"final": true, "alternatives": [{"transcript": "and the medical ID that %HESITATION had to fly ", "confidence": 0.5, "timestamps": [["and", 42.5, 42.82], ["the", 42.87, 43.05], ["medical", 43.05, 43.67], ["ID", 43.67, 43.89], ["that", 43.89, 44.12], ["%HESITATION", 44.12, 44.32], ["had", 44.32, 44.51], ["to", 44.51, 44.6], ["fly", 44.6, 45.23]]}]}, {"final": true, "alternatives": [{"transcript": "until nine ", "confidence": 0.22, "timestamps": [["until", 46.5, 47.03], ["nine", 47.03, 47.57]]}]}, {"final": true, "alternatives": [{"transcript": "David P. station they came back that and then the email pulmonary lags ", "confidence": 0.53, "timestamps": [["David", 48.79, 49.22], ["P.", 49.22, 49.56], ["station", 49.56, 50.24], ["they", 50.24, 50.34], ["came", 50.34, 50.69], ["back", 50.69, 50.99], ["that", 50.99, 51.43], ["and", 52.05, 52.28], ["then", 52.28, 52.49], ["the", 52.49, 52.59], ["email", 52.59, 53.03], ["pulmonary", 53.03, 53.73], ["lags", 53.73, 54.54]]}]}, {"final": true, "alternatives": [{"transcript": "K. Mart coowner playing guns ", "confidence": 0.54, "timestamps": [["K.", 56.8, 57.06], ["Mart", 57.06, 57.36], ["coowner", 57.36, 58.06], ["playing", 58.06, 58.43], ["guns", 58.43, 59.25]]}]}, {"final": true, "alternatives": [{"transcript": "and then there were ", "confidence": 0.61, "timestamps": [["and", 61.03, 61.19], ["then", 61.42, 61.73], ["there", 61.73, 61.97], ["were", 61.97, 62.32]]}]}, {"final": true, "alternatives": [{"transcript": "the lack I didn't see ", "confidence": 0.47, "timestamps": [["the", 63.38, 63.74], ["lack", 63.74, 64.59], ["I", 64.95, 65.23], ["didn't", 65.23, 65.66], ["see", 65.66, 66.35]]}]}, {"final": true, "alternatives": [{"transcript": "Matt ", "confidence": 0.24, "timestamps": [["Matt", 67.26, 67.85]]}]}, {"final": true, "alternatives": [{"transcript": "home alone Wednesday finishes school why did they will be gone and the oldest one who was the first Jack mmhm what we could do is to go quick ", "confidence": 0.56, "timestamps": [["home", 69.0, 69.31], ["alone", 69.35, 69.77], ["Wednesday", 69.77, 70.17], ["finishes", 70.17, 71.02], ["school", 71.02, 71.78], ["why", 72.38, 72.92], ["did", 73.45, 73.67], ["they", 73.7, 73.81], ["will", 73.81, 74.15], ["be", 74.22, 74.43], ["gone", 74.43, 74.77], ["and", 75.42, 75.64], ["the", 75.64, 75.81], ["oldest", 75.81, 76.46], ["one", 76.46, 76.68], ["who", 76.68, 76.89], ["was", 76.89, 77.26], ["the", 77.29, 77.75], ["first", 77.94, 78.24], ["Jack", 78.24, 78.81], ["mmhm", 78.93, 79.46], ["what", 79.55, 79.76], ["we", 79.76, 79.88], ["could", 79.88, 80.06], ["do", 80.06, 80.2], ["is", 80.2, 80.42], ["to", 80.42, 80.85], ["go", 81.18, 81.52], ["quick", 81.9, 82.23]]}]}, {"final": true, "alternatives": [{"transcript": "then finished that was the sense of %HESITATION the funny here ", "confidence": 0.62, "timestamps": [["then", 84.38, 84.87], ["finished", 85.28, 86.05], ["that", 86.54, 86.75], ["was", 86.75, 86.89], ["the", 86.89, 87.05], ["sense", 87.7, 88.09], ["of", 88.09, 88.16], ["%HESITATION", 88.16, 88.54], ["the", 88.54, 88.66], ["funny", 88.66, 89.03], ["here", 89.34, 89.91]]}]}]}